pyMSO4/__init__.py
pyMSO4/acquisition.py
pyMSO4/channel.py
pyMSO4/pyMSO4.py
pyMSO4/triggers.py
pyMSO4/util.py
pymso4-1.0.dist-info/METADATA
pymso4-1.0.dist-info/WHEEL
pymso4-1.0.dist-info/licenses/LICENSE
pymso4-1.0.dist-info/RECORD
