Metadata-Version: 2.1
Name: pyMSO4
Version: 1.0
Summary: Tektronix MSO4 VISA library
Project-URL: Homepage, https://ceres-c.it/pyMSO4/
Project-URL: Bug Tracker, https://github.com/ceres-c/pyMSO4/issues
Author-email: "Federico (ceres-c) Cerutti" <federico@ceres-c.it>
License-File: LICENSE
Classifier: License :: OSI Approved :: MIT License
Classifier: Operating System :: OS Independent
Classifier: Programming Language :: Python :: 3
Requires-Python: >=3.10
Requires-Dist: pyusb
Requires-Dist: pyvisa
Requires-Dist: pyvisa-py
